{
  "$schema": "../icon.schema.json",
  "use-cases": [],
  "name": "双筒望远镜",
  "tags": [
    "field眼镜",
    "搜索",
    "旅行",
    "自然",
    "研究"
  ],
  "categories": [
    "navigation",
    "nature",
    "photography",
    "science",
    "travel",
    "development"
  ],
  "i18n": {
    "en": {
      "name": "binoculars",
      "tags": [
        "field glasses",
        "lorgnette",
        "pince-nez",
        "observation",
        "sightseeing",
        "nature",
        "wildlife",
        "birdwatching",
        "scouting",
        "surveillance",
        "search",
        "discovery",
        "monitoring",
        "lookout",
        "viewpoint",
        "travel",
        "tourism",
        "research"
      ]
    }
  }
}
