{
  "$schema": "../icon.schema.json",
  "use-cases": [
    "切换蓝牙开关",
    "表示通用的无线连接功能"
  ],
  "name": "蓝牙",
  "tags": [
    "蓝牙",
    "无线",
    "连接",
    "配对",
    "设备",
    "传输"
  ],
  "categories": [
    "connectivity",
    "devices"
  ],
  "i18n": {
    "en": {
      "name": "bluetooth",
      "tags": [
        "bluetooth",
        "wireless",
        "connectivity",
        "pairing",
        "device",
        "transfer"
      ],
      "use-cases": [
        "Toggle Bluetooth on/off",
        "Represent general wireless connectivity features"
      ]
    }
  }
}
