{
  "$schema": "../icon.schema.json",
  "use-cases": [
    "游戏关卡设计",
    "地图地标",
    "奇幻主题界面"
  ],
  "name": "城堡",
  "tags": [
    "城堡",
    "堡垒",
    "宫殿",
    "建筑",
    "游戏",
    "据点"
  ],
  "categories": [
    "buildings",
    "gaming",
    "navigation"
  ],
  "i18n": {
    "en": {
      "name": "castle",
      "tags": [
        "castle",
        "fortress",
        "palace",
        "building",
        "gaming",
        "stronghold"
      ],
      "use-cases": [
        "Game level design",
        "Map landmark",
        "Fantasy theme UI"
      ]
    }
  }
}
