{
  "$schema": "../icon.schema.json",
  "use-cases": [],
  "name": "图表无坐标轴甘特图",
  "tags": [
    "时间线",
    "日期",
    "范围",
    "代码"
  ],
  "categories": [
    "charts",
    "time",
    "development",
    "design"
  ],
  "aliases": [
    {
      "name": "gantt-chart",
      "deprecated": true,
      "deprecationReason": "alias.name",
      "toBeRemovedInVersion": "v1.0"
    }
  ],
  "i18n": {
    "en": {
      "name": "chart no axes gantt",
      "tags": [
        "projects",
        "manage",
        "overview",
        "roadmap",
        "plan",
        "intentions",
        "timeline",
        "deadline",
        "date",
        "event",
        "range",
        "period",
        "productivity",
        "work",
        "agile",
        "code",
        "coding"
      ]
    }
  }
}
