{
  "$schema": "../icon.schema.json",
  "use-cases": [],
  "name": "折角箭头右",
  "tags": [
    "前进",
    "下一个",
    "更多than",
    "菜单",
    "代码",
    "命令线条",
    "终端",
    "外壳"
  ],
  "categories": [
    "arrows",
    "math",
    "development"
  ],
  "i18n": {
    "en": {
      "name": "chevron right",
      "tags": [
        "forward",
        "next",
        "more than",
        "greater",
        "menu",
        "code",
        "coding",
        "command line",
        "terminal",
        "prompt",
        "shell",
        ">"
      ]
    }
  }
}
