{
  "$schema": "../icon.schema.json",
  "use-cases": [],
  "name": "电动车充电器",
  "tags": [
    "电动",
    "充电器",
    "快速",
    "插头",
    "电动车",
    "电源",
    "电力",
    "能源"
  ],
  "categories": [
    "transportation",
    "navigation"
  ],
  "i18n": {
    "en": {
      "name": "ev charger",
      "tags": [
        "electric",
        "charger",
        "station",
        "vehicle",
        "fast",
        "plug",
        "ev",
        "power",
        "electricity",
        "energy",
        "accumulator",
        "charge"
      ]
    }
  }
}
