{
  "$schema": "../icon.schema.json",
  "use-cases": [
    "消防或紧急服务界面",
    "流行或趋势指示",
    "激情或强度象征"
  ],
  "name": "火焰",
  "tags": [
    "火焰",
    "火",
    "热",
    "燃烧",
    "紧急",
    "激情",
    "亮点"
  ],
  "categories": [
    "weather",
    "social",
    "gaming"
  ],
  "i18n": {
    "en": {
      "name": "flame",
      "tags": [
        "flame",
        "fire",
        "heat",
        "burn",
        "emergency",
        "passion",
        "hot"
      ],
      "use-cases": [
        "Fire or emergency service UI",
        "Popular or trending indicator",
        "Passion or intensity symbol"
      ]
    }
  }
}
