{
  "$schema": "../icon.schema.json",
  "use-cases": [
    "相机界面中关闭手电筒",
    "低光或省电模式",
    "工具禁用状态"
  ],
  "name": "手电筒关闭",
  "tags": [
    "手电筒关闭",
    "关闭灯光",
    "黑暗",
    "省电",
    "工具"
  ],
  "categories": [
    "photography",
    "devices"
  ],
  "i18n": {
    "en": {
      "name": "flashlight off",
      "tags": [
        "flashlight off",
        "light off",
        "dark",
        "power save",
        "tool"
      ],
      "use-cases": [
        "Toggle flashlight off in camera UI",
        "Low light or power saving mode",
        "Tool disabled state"
      ]
    }
  }
}
