{
  "$schema": "../icon.schema.json",
  "use-cases": [],
  "name": "看板",
  "tags": [
    "面板",
    "票券",
    "代码",
    "电路板"
  ],
  "categories": [
    "charts",
    "development",
    "design"
  ],
  "i18n": {
    "en": {
      "name": "kanban",
      "tags": [
        "projects",
        "manage",
        "overview",
        "board",
        "tickets",
        "issues",
        "roadmap",
        "plan",
        "intentions",
        "productivity",
        "work",
        "agile",
        "code",
        "coding"
      ]
    }
  }
}
