{
  "$schema": "../icon.schema.json",
  "use-cases": [
    "活动会话指示器",
    "运行应用状态",
    "在线状态显示"
  ],
  "name": "显示器点",
  "tags": [
    "活动状态",
    "运行中",
    "在线状态",
    "虚拟机运行",
    "桌面活跃"
  ],
  "categories": [
    "connectivity",
    "devices"
  ],
  "i18n": {
    "en": {
      "name": "monitor dot",
      "tags": [
        "active status",
        "running",
        "online status",
        "virtual machine running",
        "desktop active"
      ],
      "use-cases": [
        "Active session indicator",
        "Running application status",
        "Online presence display"
      ]
    }
  }
}
