{
  "$schema": "../icon.schema.json",
  "use-cases": [],
  "name": "滚动",
  "tags": [
    "日志",
    "便签",
    "列表",
    "代码",
    "文档",
    "故事"
  ],
  "categories": [
    "gaming",
    "development",
    "text"
  ],
  "i18n": {
    "en": {
      "name": "scroll",
      "tags": [
        "paper",
        "log",
        "scripture",
        "document",
        "notes",
        "parchment",
        "list",
        "long",
        "script",
        "story",
        "code",
        "coding"
      ]
    }
  }
}
