{
  "$schema": "../icon.schema.json",
  "use-cases": [
    "启动倒计时或计时器",
    "跟踪经过时间或持续时间",
    "设置时间限制或提醒"
  ],
  "name": "计时器",
  "tags": [
    "计时器",
    "定时器",
    "倒计时",
    "秒表",
    "时钟"
  ],
  "categories": [
    "time"
  ],
  "i18n": {
    "en": {
      "name": "timer",
      "tags": [
        "timer",
        "countdown",
        "stopwatch",
        "clock",
        "timing"
      ],
      "use-cases": [
        "Start a countdown or timer",
        "Track elapsed time or duration",
        "Set a time limit or reminder"
      ]
    }
  }
}
