{
  "$schema": "../icon.schema.json",
  "use-cases": [
    "Indicates that a service or maintenance mode is disabled",
    "Used on a button or toggle to turn service/maintenance mode off"
  ],
  "name": "扳手关闭",
  "tags": [
    "账号",
    "设置",
    "工具箱",
    "施工",
    "关闭",
    "维护",
    "禁用"
  ],
  "categories": [
    "account",
    "development",
    "tools"
  ],
  "i18n": {
    "en": {
      "name": "wrench off",
      "tags": [
        "account",
        "settings",
        "spanner",
        "diy",
        "toolbox",
        "build",
        "construction",
        "off",
        "service",
        "maintenance",
        "disabled"
      ]
    }
  }
}
